[{
  "brands": {
    "all": 0,
    "abarth": 887,
    "ac": 2459,
    "acura": 1,
    "aixam": 4,
    "aleko": 5,
    "alfa romeo": 6,
    "alpina": 7,
    "alpine": 8,
    "aro": 3,
    "asia": 10,
    "aston martin": 11,
    "audi": 12,
    "austin": 4,
    "auto union": 1,
    "autobianchi": 13,
    "barkas": 18,
    "bellier": 19,
    "bentley": 20,
    "bertone": 21,
    "bluecar": 5578,
    "bmw": 22,
    "buick": 26,
    "byd": 2484,
    "cadillac": 27,
    "casalini": 29,
    "catherham": 30,
    "chatenet": 31,
    "chevrolet": 912,
    "chrysler": 34,
    "citroen": 35,
    "cupra": 5572,
    "dacia": 37,
    "daewo": 38,
    "daihatsu": 39,
    "daimler": 40,
    "datsum": 41,
    "dfsk": 5560,
    "dodge": 46,
    "dongfeng": 2274,
    "ds": 3869,
    "e.go": 5692,
    "other": 5000,
    "unique": 293,
    "electroauto": 2404,
    "excalibur": 1258,
    "ferrari": 49,
    "fiat": 50,
    "fisker": 2427,
    "ford": 51,
    "ford (usa)": 2522,
    "fso": 195,
    "gac gonow": 2535,
    "gaz": 53,
    "genesis": 2929,
    "gmc": 55,
    "great wall": 2409,
    "hanomag": 447,
    "honda": 59,
    "hummer": 61,
    "hyundai": 62,
    "ineos": 5713,
    "infiniti": 63,
    "innocenti": 64,
    "isuzu": 66,
    "iveco": 208,
    "jaguar": 67,
    "jdm": 68,
    "jeep": 69,
    "kia": 71,
    "ktm": 353,
    "lada": 72,
    "lamborghini": 73,
    "lancia": 74,
    "land rover": 75,
    "levc": 5550,
    "lexus": 77,
    "ligier": 78,
    "lincoln": 79,
    "london": 3693,
    "lotus": 80,
    "lti (carbodies)": 2268,
    "luaz": 882,
    "mahindra": 81,
    "maruti": 83,
    "maserati": 84,
    "maxus": 5634,
    "maybach": 86,
    "mazda": 85,
    "mclaren": 2294,
    "mega": 236,
    "mercedes-amg": 3768,
    "mercedes-benz": 87,
    "mercedes-maybach": 3833,
    "mercury": 88,
    "mg": 89,
    "microcar": 90,
    "mini": 91,
    "mitsubishi": 92,
    "morgan": 93,
    "morris": 568,
    "moszkvics": 94,
    "nissan": 95,
    "nsu": 96,
    "oldsmobile": 98,
    "opel": 100,
    "panhard": 3680,
    "peugeot": 103,
    "pgo": 104,
    "plymouth": 105,
    "polaris": 394,
    "polestar": 5639,
    "polski fiat": 108,
    "pontiac": 107,
    "porsche": 109,
    "proton": 110,
    "renault": 114,
    "replika": 3681,
    "reva": 115,
    "rolls-royce": 116,
    "rover": 117,
    "saab": 118,
    "seat": 122,
    "shanghai gm (chevrolet)": 2596,
    "shuanghuan": 123,
    "simca": 125,
    "skoda": 124,
    "smart": 126,
    "ssangyong": 128,
    "steyr puch": 129,
    "subaru": 131,
    "suzuki": 133,
    "talbot": 134,
    "tata": 135,
    "tesla": 2269,
    "toyota": 138,
    "trabant": 139,
    "triumph": 140,
    "uaz": 141,
    "vauxhall": 143,
    "versenyautó": 567,
    "volga": 145,
    "volkswagen": 146,
    "volvo": 147,
    "wartburg": 148,
    "wiesmann": 150,
    "xev": 5689,
    "yugo": 152,
    "zaporozsec": 153,
    "zastava": 154,
    "zhidou": 5579
  }
}]